sanic_restful_framework-0.0.1.dist-info/licenses/LICENSE
srf/__init__.py
srf/exceptions.py
srf/paginator.py
srf/route.py
srf/auth/__init__.py
srf/auth/auth.py
srf/auth/models.py
srf/auth/route.py
srf/auth/schema.py
srf/auth/social_auth.py
srf/auth/viewset.py
srf/config/__init__.py
srf/config/settings.py
srf/event/__init__.py
srf/event/route.py
srf/event/viewset.py
srf/filters/__init__.py
srf/filters/filter.py
srf/health/__init__.py
srf/health/base.py
srf/health/checks.py
srf/health/route.py
srf/middleware/__init__.py
srf/middleware/authmiddleware.py
srf/middleware/csrfmiddleware.py
srf/middleware/throttemiddleware.py
srf/permission/permission.py
srf/tools/email.py
srf/tools/utils.py
srf/views/__init__.py
srf/views/base.py
srf/views/decorators.py
srf/views/http_status.py
tests/test_decorators.py
tests/test_filters.py
tests/test_middleware.py
tests/test_paginator.py
tests/test_permission.py
tests/test_route.py
tests/test_tools.py
tests/test_views.py
sanic_restful_framework-0.0.1.dist-info/METADATA
sanic_restful_framework-0.0.1.dist-info/WHEEL
sanic_restful_framework-0.0.1.dist-info/top_level.txt
sanic_restful_framework-0.0.1.dist-info/RECORD
