Metadata-Version: 2.4
Name: sanic-restful-framework
Version: 0.0.1
Summary: Sanic REST Framework - A fast, async REST API framework for Sanic
Author-email: Chacer <1364707405c@gmail.com>
License: MIT
Project-URL: Homepage, https://github.com/*
Requires-Python: >=3.11
License-File: LICENSE
Requires-Dist: aiohttp<4,>=3.13
Requires-Dist: bcrypt>=4.1.2
Requires-Dist: packaging<27,>=26
Requires-Dist: pydantic<3,>=2.6.1
Requires-Dist: pydantic_core<3,>=2.41
Requires-Dist: PyJWT<3,>=2.10
Requires-Dist: redis<8,>=7.1
Requires-Dist: sanic<26,>=25.0.0
Requires-Dist: sanic_jwt<2,>=1.8.0
Requires-Dist: tortoise-orm==0.25.1
Provides-Extra: dev
Requires-Dist: pytest<10,>=9.0; extra == "dev"
Requires-Dist: black; extra == "dev"
Requires-Dist: isort; extra == "dev"
Requires-Dist: ruff; extra == "dev"
Requires-Dist: build; extra == "dev"
Dynamic: license-file
